{
  "total": 144,
  "rows": [
    {
      "searchValue": null,
      "createBy": null,
      "createTime": null,
      "updateBy": null,
      "updateTime": null,
      "remark": null,
      "dataScope": null,
      "operId": 100,
      "title": "部门管理",
      "businessType": 1,
      "businessTypes": null,
      "method": "com.growup.project.system.controller.SysDeptController.add()",
      "requestMethod": "POST",
      "operatorType": 1,
      "operName": "admin",
      "deptName": null,
      "operUrl": "/system/dept",
      "operIp": "192.168.0.103",
      "operLocation": "内网IP",
      "operParam": "{\"deptName\":\"测试部门\",\"orderNum\":\"3\",\"params\":{},\"parentId\":102,\"createBy\":\"admin\",\"children\":[],\"ancestors\":\"0,100,102\",\"status\":\"0\"}",
      "jsonResult": "{\"msg\":\"操作成功\",\"code\":200}",
      "status": 0,
      "errorMsg": null,
      "operTime": "2019-10-28T08:27:36.000+0000"
    },
    {
      "searchValue": null,
      "createBy": null,
      "createTime": null,
      "updateBy": null,
      "updateTime": null,
      "remark": null,
      "dataScope": null,
      "operId": 101,
      "title": "部门管理",
      "businessType": 3,
      "businessTypes": null,
      "method": "com.growup.project.system.controller.SysDeptController.remove()",
      "requestMethod": "DELETE",
      "operatorType": 1,
      "operName": "admin",
      "deptName": null,
      "operUrl": "/system/dept/200",
      "operIp": "192.168.0.103",
      "operLocation": "内网IP",
      "operParam": "{deptId=200}",
      "jsonResult": "{\"msg\":\"操作成功\",\"code\":200}",
      "status": 0,
      "errorMsg": null,
      "operTime": "2019-10-28T08:27:44.000+0000"
    },
    {
      "searchValue": null,
      "createBy": null,
      "createTime": null,
      "updateBy": null,
      "updateTime": null,
      "remark": null,
      "dataScope": null,
      "operId": 102,
      "title": "菜单管理",
      "businessType": 1,
      "businessTypes": null,
      "method": "com.growup.project.system.controller.SysMenuController.add()",
      "requestMethod": "POST",
      "operatorType": 1,
      "operName": "admin",
      "deptName": null,
      "operUrl": "/system/menu",
      "operIp": "192.168.0.103",
      "operLocation": "内网IP",
      "operParam": "{\"visible\":\"0\",\"icon\":\"tree\",\"orderNum\":\"5\",\"menuName\":\"测试\",\"params\":{},\"createBy\":\"admin\",\"children\":[],\"isFrame\":\"1\",\"menuType\":\"M\"}",
      "jsonResult": "{\"msg\":\"操作成功\",\"code\":200}",
      "status": 0,
      "errorMsg": null,
      "operTime": "2019-10-28T08:43:19.000+0000"
    },
    {
      "searchValue": null,
      "createBy": null,
      "createTime": null,
      "updateBy": null,
      "updateTime": null,
      "remark": null,
      "dataScope": null,
      "operId": 103,
      "title": "菜单管理",
      "businessType": 2,
      "businessTypes": null,
      "method": "com.growup.project.system.controller.SysMenuController.edit()",
      "requestMethod": "PUT",
      "operatorType": 1,
      "operName": "admin",
      "deptName": null,
      "operUrl": "/system/menu",
      "operIp": "192.168.0.103",
      "operLocation": "内网IP",
      "operParam": "{\"visible\":\"1\",\"icon\":\"tree\",\"orderNum\":\"5\",\"menuName\":\"测试\",\"params\":{},\"parentId\":0,\"path\":\"\",\"children\":[],\"createTime\":1572252198000,\"updateBy\":\"admin\",\"isFrame\":\"1\",\"menuId\":2000,\"menuType\":\"M\",\"perms\":\"\"}",
      "jsonResult": "{\"msg\":\"操作成功\",\"code\":200}",
      "status": 0,
      "errorMsg": null,
      "operTime": "2019-10-28T08:44:47.000+0000"
    },
    {
      "searchValue": null,
      "createBy": null,
      "createTime": null,
      "updateBy": null,
      "updateTime": null,
      "remark": null,
      "dataScope": null,
      "operId": 104,
      "title": "菜单管理",
      "businessType": 2,
      "businessTypes": null,
      "method": "com.growup.project.system.controller.SysMenuController.edit()",
      "requestMethod": "PUT",
      "operatorType": 1,
      "operName": "admin",
      "deptName": null,
      "operUrl": "/system/menu",
      "operIp": "192.168.0.102",
      "operLocation": "内网IP",
      "operParam": "{\"visible\":\"1\",\"icon\":\"tree\",\"orderNum\":\"5\",\"menuName\":\"测试\",\"params\":{},\"parentId\":0,\"path\":\"\",\"children\":[],\"createTime\":1572252198000,\"updateBy\":\"admin\",\"isFrame\":\"1\",\"menuId\":2000,\"menuType\":\"F\",\"perms\":\"\"}",
      "jsonResult": "{\"msg\":\"操作成功\",\"code\":200}",
      "status": 0,
      "errorMsg": null,
      "operTime": "2019-10-29T09:21:29.000+0000"
    },
    {
      "searchValue": null,
      "createBy": null,
      "createTime": null,
      "updateBy": null,
      "updateTime": null,
      "remark": null,
      "dataScope": null,
      "operId": 105,
      "title": "菜单管理",
      "businessType": 2,
      "businessTypes": null,
      "method": "com.growup.project.system.controller.SysMenuController.edit()",
      "requestMethod": "PUT",
      "operatorType": 1,
      "operName": "admin",
      "deptName": null,
      "operUrl": "/system/menu",
      "operIp": "192.168.0.102",
      "operLocation": "内网IP",
      "operParam": "{\"visible\":\"1\",\"icon\":\"tree\",\"orderNum\":\"5\",\"menuName\":\"测试\",\"params\":{},\"parentId\":0,\"path\":\"\",\"children\":[],\"createTime\":1572252198000,\"updateBy\":\"admin\",\"isFrame\":\"1\",\"menuId\":2000,\"menuType\":\"C\",\"perms\":\"\"}",
      "jsonResult": "{\"msg\":\"操作成功\",\"code\":200}",
      "status": 0,
      "errorMsg": null,
      "operTime": "2019-10-29T09:21:48.000+0000"
    },
    {
      "searchValue": null,
      "createBy": null,
      "createTime": null,
      "updateBy": null,
      "updateTime": null,
      "remark": null,
      "dataScope": null,
      "operId": 106,
      "title": "菜单管理",
      "businessType": 2,
      "businessTypes": null,
      "method": "com.growup.project.system.controller.SysMenuController.edit()",
      "requestMethod": "PUT",
      "operatorType": 1,
      "operName": "admin",
      "deptName": null,
      "operUrl": "/system/menu",
      "operIp": "192.168.0.102",
      "operLocation": "内网IP",
      "operParam": "{\"visible\":\"1\",\"icon\":\"tree\",\"orderNum\":\"5\",\"menuName\":\"测试\",\"params\":{},\"parentId\":0,\"path\":\"build\",\"children\":[],\"createTime\":1572252198000,\"updateBy\":\"admin\",\"isFrame\":\"1\",\"menuId\":2000,\"menuType\":\"C\",\"perms\":\"\"}",
      "jsonResult": "{\"msg\":\"操作成功\",\"code\":200}",
      "status": 0,
      "errorMsg": null,
      "operTime": "2019-10-29T09:23:00.000+0000"
    },
    {
      "searchValue": null,
      "createBy": null,
      "createTime": null,
      "updateBy": null,
      "updateTime": null,
      "remark": null,
      "dataScope": null,
      "operId": 107,
      "title": "菜单管理",
      "businessType": 2,
      "businessTypes": null,
      "method": "com.growup.project.system.controller.SysMenuController.edit()",
      "requestMethod": "PUT",
      "operatorType": 1,
      "operName": "admin",
      "deptName": null,
      "operUrl": "/system/menu",
      "operIp": "192.168.0.102",
      "operLocation": "内网IP",
      "operParam": "{\"visible\":\"0\",\"icon\":\"tree\",\"orderNum\":\"5\",\"menuName\":\"测试\",\"params\":{},\"parentId\":0,\"path\":\"build\",\"component\":\"tool/build/index\",\"children\":[],\"createTime\":1572252198000,\"updateBy\":\"admin\",\"isFrame\":\"1\",\"menuId\":2000,\"menuType\":\"C\",\"perms\":\"\"}",
      "jsonResult": "{\"msg\":\"操作成功\",\"code\":200}",
      "status": 0,
      "errorMsg": null,
      "operTime": "2019-10-29T09:23:24.000+0000"
    },
    {
      "searchValue": null,
      "createBy": null,
      "createTime": null,
      "updateBy": null,
      "updateTime": null,
      "remark": null,
      "dataScope": null,
      "operId": 108,
      "title": "菜单管理",
      "businessType": 2,
      "businessTypes": null,
      "method": "com.growup.project.system.controller.SysMenuController.edit()",
      "requestMethod": "PUT",
      "operatorType": 1,
      "operName": "admin",
      "deptName": null,
      "operUrl": "/system/menu",
      "operIp": "192.168.0.102",
      "operLocation": "内网IP",
      "operParam": "{\"visible\":\"0\",\"icon\":\"tree\",\"orderNum\":\"5\",\"menuName\":\"测试\",\"params\":{},\"parentId\":0,\"path\":\"build\",\"component\":\"tool/build/index\",\"children\":[],\"createTime\":1572252198000,\"updateBy\":\"admin\",\"isFrame\":\"1\",\"menuId\":2000,\"menuType\":\"C\",\"perms\":\"tool:build:list\"}",
      "jsonResult": "{\"msg\":\"操作成功\",\"code\":200}",
      "status": 0,
      "errorMsg": null,
      "operTime": "2019-10-29T09:24:10.000+0000"
    },
    {
      "searchValue": null,
      "createBy": null,
      "createTime": null,
      "updateBy": null,
      "updateTime": null,
      "remark": null,
      "dataScope": null,
      "operId": 109,
      "title": "菜单管理",
      "businessType": 2,
      "businessTypes": null,
      "method": "com.growup.project.system.controller.SysMenuController.edit()",
      "requestMethod": "PUT",
      "operatorType": 1,
      "operName": "admin",
      "deptName": null,
      "operUrl": "/system/menu",
      "operIp": "192.168.0.102",
      "operLocation": "内网IP",
      "operParam": "{\"visible\":\"0\",\"icon\":\"tree\",\"orderNum\":\"5\",\"menuName\":\"测试\",\"params\":{},\"parentId\":0,\"path\":\"build\",\"component\":\"tool/test/index\",\"children\":[],\"createTime\":1572252198000,\"updateBy\":\"admin\",\"isFrame\":\"1\",\"menuId\":2000,\"menuType\":\"C\",\"perms\":\"tool:build:list\"}",
      "jsonResult": "{\"msg\":\"操作成功\",\"code\":200}",
      "status": 0,
      "errorMsg": null,
      "operTime": "2019-10-29T11:34:13.000+0000"
    }
  ]
}
